explainableai/__init__.py
explainableai/anomaly_detection.py
explainableai/core.py
explainableai/exceptions.py
explainableai/fairness.py
explainableai/feature_analysis.py
explainableai/feature_engineering.py
explainableai/feature_interaction.py
explainableai/feature_selection.py
explainableai/llm_explanations.py
explainableai/logging_config.py
explainableai/model_comparison.py
explainableai/model_evaluation.py
explainableai/model_interpretability.py
explainableai/model_selection.py
explainableai/report_generator.py
explainableai/utils.py
explainableai/visualizations.py
explainableai-0.10.dist-info/LICENSE.md
explainableai-0.10.dist-info/METADATA
explainableai-0.10.dist-info/WHEEL
explainableai-0.10.dist-info/entry_points.txt
explainableai-0.10.dist-info/top_level.txt
explainableai-0.10.dist-info/RECORD
