Metadata-Version: 2.1
Name: explainableai
Version: 0.10
Summary: A comprehensive package for Explainable AI and model interpretation
Home-page: https://github.com/ombhojane/explainableai
Author: Om Bhojane, Palak Boricha
Author-email: ombhojane05@gmail.com
Project-URL: Bug Tracker, https://github.com/ombhojane/explainableai/issues
Project-URL: Source Code, https://github.com/ombhojane/explainableai
Keywords: explainableai,explainable ai,interpretable ml,model interpretability,feature importance,shap,lime,model explanation,ai transparency,machine learning,deep learning,artificial intelligence,data science,model insights,feature analysis,model debugging,ai ethics,responsible ai,xai,model visualization
Classifier: Development Status :: 3 - Alpha
Classifier: Intended Audience :: Developers
Classifier: Intended Audience :: Science/Research
Classifier: License :: OSI Approved :: MIT License
Classifier: Operating System :: OS Independent
Classifier: Programming Language :: Python :: 3
Classifier: Programming Language :: Python :: 3.7
Classifier: Programming Language :: Python :: 3.8
Classifier: Programming Language :: Python :: 3.9
Classifier: Programming Language :: Python :: 3.10
Classifier: Programming Language :: Python :: 3.11
Classifier: Programming Language :: Python :: 3.12
Classifier: Topic :: Scientific/Engineering :: Artificial Intelligence
Classifier: Topic :: Software Development :: Libraries :: Python Modules
Requires-Python: >=3.7
License-File: LICENSE.md
Requires-Dist: numpy
Requires-Dist: pandas
Requires-Dist: scikit-learn
Requires-Dist: shap
Requires-Dist: matplotlib
Requires-Dist: seaborn
Requires-Dist: plotly
Requires-Dist: ipywidgets
Requires-Dist: lime
Requires-Dist: reportlab
Requires-Dist: google-generativeai
Requires-Dist: python-dotenv
Requires-Dist: scipy
Requires-Dist: pillow
Requires-Dist: colorama
Requires-Dist: dask
Provides-Extra: dev
Requires-Dist: pytest ; extra == 'dev'
Requires-Dist: flake8 ; extra == 'dev'
Requires-Dist: black ; extra == 'dev'
Requires-Dist: mypy ; extra == 'dev'
